csfloat_api/__init__.py
csfloat_api/csfloat_client.py
csfloat_api/models/__init__.py
csfloat_api/models/auction.py
csfloat_api/models/buy_orders.py
csfloat_api/models/item.py
csfloat_api/models/listing.py
csfloat_api/models/me.py
csfloat_api/models/reference.py
csfloat_api/models/seller.py
csfloat_api/models/stall.py
csfloat_api/models/statistics.py
csfloat_api/models/stickers.py
csfloat_api-1.3.0.dist-info/METADATA
csfloat_api-1.3.0.dist-info/WHEEL
csfloat_api-1.3.0.dist-info/top_level.txt
csfloat_api-1.3.0.dist-info/RECORD
