Metadata-Version: 2.4
Name: csfloat_api
Version: 1.3.0
Summary: This is an unofficial Python client library for interacting with the CSFloat API. The library allows users to programmatically access CSFloat’s listings, buy orders, user information, exchange rates, and more.
Home-page: https://github.com/Rushifakami/csfloat_api
Author: Rushifakami
License: MIT
Classifier: Development Status :: 5 - Production/Stable
Classifier: Intended Audience :: Developers
Classifier: License :: OSI Approved :: MIT License
Classifier: Programming Language :: Python :: 3
Classifier: Programming Language :: Python :: 3.6
Classifier: Programming Language :: Python :: 3.7
Classifier: Programming Language :: Python :: 3.8
Classifier: Programming Language :: Python :: 3.9
Classifier: Programming Language :: Python :: 3.10
Classifier: Programming Language :: Python :: 3.11
Classifier: Programming Language :: Python :: 3.12
Requires-Python: >=3.6
Requires-Dist: aiohttp
Requires-Dist: aiohttp_socks
Dynamic: author
Dynamic: classifier
Dynamic: description
Dynamic: description-content-type
Dynamic: home-page
Dynamic: license
Dynamic: requires-dist
Dynamic: requires-python
Dynamic: summary
